{
  "date": "2026-06-18",
  "generated_at": "2026-06-19T00:19:59.677768+00:00",
  "count": 1,
  "matches": [
    {
      "match": {
        "home_team": "Galvez U20",
        "away_team": "Independencia U20",
        "league": "BRAZIL: Acreano U20",
        "date": "2026-06-18T23:00:00+00:00",
        "venue": "",
        "status": "UPCOMING",
        "event_id": "x6hH6z2b",
        "id": "x6hH6z2b"
      },
      "prediction": {
        "home_win_prob": 47.23,
        "draw_prob": 23.84,
        "away_win_prob": 28.93,
        "predicted_outcome": "HOME_WIN",
        "confidence": "MEDIUM",
        "confidence_score": 66,
        "missing_data": [
          "injuries",
          "referee",
          "weather"
        ],
        "proxy_factors": [
          "xg"
        ],
        "lambda": {
          "home": 1.8362,
          "away": 1.3972
        },
        "predicted_goals": {
          "home": 1.821,
          "away": 1.389
        },
        "most_likely_scores": [
          {
            "score": "1-1",
            "prob": 11.43
          },
          {
            "score": "2-1",
            "prob": 9.29
          },
          {
            "score": "1-2",
            "prob": 7.07
          },
          {
            "score": "2-0",
            "prob": 6.65
          },
          {
            "score": "2-2",
            "prob": 6.49
          }
        ],
        "monte_carlo": {
          "simulations": 10000,
          "home_win": 47.87,
          "draw": 22.32,
          "away_win": 29.81,
          "confidence_interval": "±1.0%",
          "histogram": {
            "0": 4.29,
            "1": 12.68,
            "2": 20.38,
            "3": 23.26,
            "4": 17.27,
            "5": 11.49,
            "6": 6.01,
            "7": 2.69,
            "8": 1.93
          },
          "top_scores": [
            {
              "score": "1-1",
              "prob": 10.02
            },
            {
              "score": "2-1",
              "prob": 9.33
            },
            {
              "score": "1-2",
              "prob": 7.42
            },
            {
              "score": "1-0",
              "prob": 7.13
            },
            {
              "score": "2-0",
              "prob": 6.41
            }
          ]
        }
      },
      "markets": {
        "over_under_2_5": {
          "over": 62.68,
          "under": 37.32
        },
        "btts": {
          "yes": 63.58,
          "no": 36.42
        }
      },
      "value_bets": [
        {
          "market": "O/U 2.5",
          "pick": "Under 2.5",
          "our_prob": 37.32,
          "implied_prob": 21.74,
          "value": 15.58,
          "kelly_pct": 19.91,
          "half_kelly_pct": 9.95,
          "rating": "STRONG_VALUE",
          "odds": 4.6
        },
        {
          "market": "BTTS",
          "pick": "No",
          "our_prob": 36.42,
          "implied_prob": 21.83,
          "value": 14.59,
          "kelly_pct": 18.66,
          "half_kelly_pct": 9.33,
          "rating": "STRONG_VALUE",
          "odds": 4.58
        },
        {
          "market": "1X2",
          "pick": "Home Win",
          "our_prob": 47.23,
          "implied_prob": 38.02,
          "value": 9.21,
          "kelly_pct": 14.86,
          "half_kelly_pct": 7.43,
          "rating": "GOOD_VALUE",
          "odds": 2.63
        },
        {
          "market": "1X2",
          "pick": "Draw",
          "our_prob": 23.84,
          "implied_prob": 22.88,
          "value": 0.96,
          "kelly_pct": 1.24,
          "half_kelly_pct": 0.62,
          "rating": "SLIGHT_VALUE",
          "odds": 4.37
        }
      ],
      "breakdown": {
        "form": {
          "home_last5": [
            "W",
            "L",
            "W",
            "L",
            "W"
          ],
          "away_last5": [
            "W",
            "W",
            "W",
            "W",
            "D"
          ],
          "home_form_score": 60,
          "away_form_score": 97
        },
        "h2h": {
          "home_wins": 1,
          "draws": 0,
          "away_wins": 0,
          "avg_goals": 8.0,
          "matches": 1
        },
        "xg": {
          "home_xg": 2.0,
          "home_xga": 1.333,
          "away_xg": 6.667,
          "away_xga": 0.0,
          "home_source": "goals",
          "away_source": "goals",
          "is_proxy": true
        },
        "standings": {
          "home_pos": null,
          "away_pos": null,
          "points_diff": null
        },
        "injuries": {
          "home_missing": [],
          "away_missing": []
        },
        "referee": null,
        "fatigue": {
          "home_rest_days": 7,
          "away_rest_days": 5,
          "home_status": "FRESH",
          "away_status": "FRESH"
        },
        "weather": null,
        "factors_used": {
          "weights": {
            "form": 0.45,
            "xg": 0.2,
            "attack_defense": 0.18,
            "home": 0.07,
            "h2h": 0.05,
            "fatigue": 0.05
          },
          "form": {
            "home_form_score": 1.8,
            "away_form_score": 2.0,
            "home_matches": [
              {
                "opponent": "Andira U20",
                "position": 6,
                "position_estimated": false,
                "venue": "away",
                "outcome": "W",
                "score": "2-1",
                "points": 3
              },
              {
                "opponent": "Santa Cruz U20",
                "position": 1,
                "position_estimated": false,
                "venue": "away",
                "outcome": "L",
                "score": "0-2",
                "points": 1
              },
              {
                "opponent": "Nauas EC U20",
                "position": 9,
                "position_estimated": false,
                "venue": "away",
                "outcome": "W",
                "score": "4-1",
                "points": 2
              },
              {
                "opponent": "Sao Francisco U20",
                "position": 3,
                "position_estimated": false,
                "venue": "home",
                "outcome": "L",
                "score": "1-7",
                "points": 0
              },
              {
                "opponent": "Vasco da Gama AC U20",
                "position": 7,
                "position_estimated": false,
                "venue": "away",
                "outcome": "W",
                "score": "5-1",
                "points": 3
              }
            ],
            "away_matches": [
              {
                "opponent": "Placido de Castro U20",
                "position": 8,
                "position_estimated": false,
                "venue": "home",
                "outcome": "W",
                "score": "9-0",
                "points": 2
              },
              {
                "opponent": "Andira U20",
                "position": 6,
                "position_estimated": false,
                "venue": "home",
                "outcome": "W",
                "score": "2-0",
                "points": 2
              },
              {
                "opponent": "Nauas EC U20",
                "position": 9,
                "position_estimated": false,
                "venue": "away",
                "outcome": "W",
                "score": "9-0",
                "points": 2
              },
              {
                "opponent": "Vasco da Gama AC U20",
                "position": 7,
                "position_estimated": false,
                "venue": "away",
                "outcome": "W",
                "score": "7-3",
                "points": 3
              },
              {
                "opponent": "Assermurb U20",
                "position": 4,
                "position_estimated": false,
                "venue": "home",
                "outcome": "D",
                "score": "0-0",
                "points": 1
              }
            ]
          },
          "home_factors": {
            "form": {
              "weight": 0.45,
              "weight_norm": 0.45,
              "mult": 1.06,
              "contribution": 0.041
            },
            "xg": {
              "weight": 0.2,
              "weight_norm": 0.2,
              "mult": 1.333,
              "contribution": 0.1
            },
            "attack_defense": {
              "weight": 0.18,
              "weight_norm": 0.18,
              "mult": 1.6,
              "contribution": 0.162
            },
            "home": {
              "weight": 0.07,
              "weight_norm": 0.07,
              "mult": 1.2,
              "contribution": 0.021
            },
            "h2h": {
              "weight": 0.05,
              "weight_norm": 0.05,
              "mult": 1.15,
              "contribution": 0.011
            },
            "fatigue": {
              "weight": 0.05,
              "weight_norm": 0.05,
              "mult": 1.02,
              "contribution": 0.002
            }
          },
          "away_factors": {
            "form": {
              "weight": 0.45,
              "weight_norm": 0.45,
              "mult": 1.1,
              "contribution": 0.052
            },
            "xg": {
              "weight": 0.2,
              "weight_norm": 0.2,
              "mult": 1.4,
              "contribution": 0.092
            },
            "attack_defense": {
              "weight": 0.18,
              "weight_norm": 0.18,
              "mult": 1.6,
              "contribution": 0.124
            },
            "home": {
              "weight": 0.07,
              "weight_norm": 0.07,
              "mult": 0.85,
              "contribution": -0.012
            },
            "h2h": {
              "weight": 0.05,
              "weight_norm": 0.05,
              "mult": 0.85,
              "contribution": -0.009
            },
            "fatigue": {
              "weight": 0.05,
              "weight_norm": 0.05,
              "mult": 1.0,
              "contribution": 0.0
            }
          },
          "base": {
            "home_goals": 1.5,
            "away_goals": 1.15
          },
          "lambda": {
            "home": 1.836,
            "away": 1.397
          }
        },
        "positions_estimated": 0,
        "notes": []
      },
      "poisson_matrix": [
        [
          5.257,
          4.193,
          3.848,
          1.792,
          0.626,
          0.175,
          0.051
        ],
        [
          5.924,
          11.429,
          7.066,
          3.291,
          1.149,
          0.321,
          0.093
        ],
        [
          6.646,
          9.286,
          6.487,
          3.021,
          1.055,
          0.295,
          0.085
        ],
        [
          4.068,
          5.684,
          3.971,
          1.849,
          0.646,
          0.18,
          0.052
        ],
        [
          1.867,
          2.609,
          1.823,
          0.849,
          0.297,
          0.083,
          0.024
        ],
        [
          0.686,
          0.958,
          0.669,
          0.312,
          0.109,
          0.03,
          0.009
        ],
        [
          0.281,
          0.392,
          0.274,
          0.128,
          0.045,
          0.012,
          0.004
        ]
      ],
      "poisson_matrix_sum": 100.0,
      "odds": {
        "home": 2.63,
        "draw": 4.37,
        "away": 2.12,
        "over_2_5": 1.15,
        "under_2_5": 4.6,
        "btts_yes": 1.15,
        "btts_no": 4.58
      },
      "implied_probs": {
        "home": 38.02,
        "draw": 22.88,
        "away": 47.17
      },
      "data_sources": [
        "flashscore",
        "flashscore-odds",
        "flashscore-feed",
        "flashscore-standings",
        "flashscore-stats"
      ],
      "computed_at": "2026-06-19T00:19:48.395122+00:00"
    }
  ]
}